evm_sc_utils/__init__.py
evm_sc_utils/merkle_tree.py
evm_sc_utils/signers.py
evm_sc_utils-0.3.0.dist-info/LICENSE
evm_sc_utils-0.3.0.dist-info/WHEEL
evm_sc_utils-0.3.0.dist-info/METADATA
evm_sc_utils-0.3.0.dist-info/RECORD
